{
  "author": "杨无咎",
  "poem_count": 177,
  "poem_type_counts": {
    "词": 177
  },
  "meter_patterns": [
    {
      "pattern": "4,4,4,4,4,4,6,3,4,4,4,4",
      "count": 20
    },
    {
      "pattern": "4,7,4,5,4,5,3,4,5",
      "count": 5
    },
    {
      "pattern": "7,5,5,4,5,7,5,5,4,5",
      "count": 5
    },
    {
      "pattern": "7,3,3,7,4,4,5,7,7,7,4,4,5",
      "count": 4
    },
    {
      "pattern": "3,5,7,7,5,3,5,7,7,5",
      "count": 4
    },
    {
      "pattern": "7,4,5,7,7,7,4,5,7,7",
      "count": 4
    },
    {
      "pattern": "4,5,5,3,4,4,5,3,3,5,4,5,5,3,4,4,5,3,3,5",
      "count": 4
    },
    {
      "pattern": "7,7,7,7,3,3,7,7,7",
      "count": 4
    },
    {
      "pattern": "7,3,4,7,3,3,7,3,4,7,3,3",
      "count": 3
    },
    {
      "pattern": "5,4,4,4,5,4,4,5,4,4,4,4,4,4,4,4,5,4,4,5,4,4,4",
      "count": 3
    },
    {
      "pattern": "5,5,7,5,5,5,7,5",
      "count": 3
    },
    {
      "pattern": "5,3,6,5,3,6,4,3,4,5,4,4,2,4,4,4,4,3,3,3,6,6,5,6",
      "count": 3
    },
    {
      "pattern": "7,7,7,7,7,7,7,7",
      "count": 3
    },
    {
      "pattern": "7,7,7,3,7,7,7,7,3,7",
      "count": 3
    },
    {
      "pattern": "5,5,7,6,3,5,5,7,6,3",
      "count": 3
    },
    {
      "pattern": "5,5,5,5,5,5,5,5",
      "count": 3
    },
    {
      "pattern": "6,3,4,4,4,5,7,3,4,4,4,5",
      "count": 3
    },
    {
      "pattern": "6,7,4,4,4,4,4,4,5,4,3,3,6,3,4,4,4,4,4,4,4,5,4,4",
      "count": 2
    },
    {
      "pattern": "4,6,5,3,3,5,3,5,4,6,4,5,5,3,5",
      "count": 2
    },
    {
      "pattern": "5,5,4,7,6,6,5,5,5,3,3,3,4,7,6,6,5,5,5",
      "count": 2
    },
    {
      "pattern": "5,5,6,5,6,6,5,5,5,3,3,3,4,7,6,6,5,5,5",
      "count": 2
    },
    {
      "pattern": "7,6,4,4,6,4,5,4,4,7,6,5,4,4,4,6,4,5,4,4,5",
      "count": 2
    },
    {
      "pattern": "7,5,6,6,4,4,4,6,6",
      "count": 2
    },
    {
      "pattern": "7,3,3,7,5,7,3,3,7,5",
      "count": 2
    },
    {
      "pattern": "4,4,6,5,4,4,4,4,5,4,4,4,4,6,3,4,4,6,6,4,4,4",
      "count": 2
    },
    {
      "pattern": "5,3,3,5,5,5,5,5,6,4,7,5,5,4,5,4,5",
      "count": 2
    },
    {
      "pattern": "4,5,7,6,6,6,6,6",
      "count": 2
    },
    {
      "pattern": "7,3,3,7,3,3,7,3,3,7,3,3",
      "count": 2
    },
    {
      "pattern": "4,4,4,4,4,5,4,4,6,3,4,6,4,4,6,4,4,5,4,4,6,3,4,4",
      "count": 2
    },
    {
      "pattern": "4,4,4,3,5,3,3,7,5,3,5,3,3",
      "count": 2
    },
    {
      "pattern": "7,5,4,4,4,4,4,4,7,5",
      "count": 2
    },
    {
      "pattern": "5,5,7,6,4,5,5,7,6,4",
      "count": 2
    },
    {
      "pattern": "6,6,7,6,6,6,7,6",
      "count": 2
    },
    {
      "pattern": "4,4,3,4,3,4,3,4,4,6,4,3,4,3,4,3,4,4",
      "count": 2
    },
    {
      "pattern": "4,5,4,4,4,5,5,3,3,4,4,4,2,4,3,4,5,4,5,5,7,3,4,6",
      "count": 2
    },
    {
      "pattern": "7,3,3,4,4,4,4,4,4,5,4,3,3,6,3,4,4,4,4,4,4,4,5,4,4",
      "count": 1
    },
    {
      "pattern": "7,3,3,4,4,4,4,4,4,5,4,3,3,6,3,4,4,4,4,4,4,4,3,4,6",
      "count": 1
    },
    {
      "pattern": "6,7,4,4,4,4,4,4,5,4,3,3,6,3,4,6,6,4,4,4,5,4,4",
      "count": 1
    },
    {
      "pattern": "6,7,4,4,4,4,4,4,5,4,6,6,3,4,4,4,4,4,4,4,5,4,4",
      "count": 1
    },
    {
      "pattern": "4,5,4,4,3,6,4,4,5,4,6,6,5,4,4,3,6,4,4,5,4,6",
      "count": 1
    },
    {
      "pattern": "4,5,4,4,5,4,4,6,3,5,4,5,5,4,4,5,4,4,6,3,3,4",
      "count": 1
    },
    {
      "pattern": "6,5,5,6,5,3,5,3,4,6,4,6,7,2,6",
      "count": 1
    },
    {
      "pattern": "4,3,3,7,4,5,7,3,4,7,3,5",
      "count": 1
    },
    {
      "pattern": "3,3,6,5,3,7,4,3,4,7,6,3,5,3,4,6,3,4,6,3,4,3,5,4",
      "count": 1
    },
    {
      "pattern": "4,3,6,4,4,6,3,3,4,3,4,5,6,4,3,6,5,3,4,5,4,6",
      "count": 1
    },
    {
      "pattern": "6,5,4,5,6,4,3,3,3,6,5,9,6,4,3,3",
      "count": 1
    },
    {
      "pattern": "4,8,7,4,5,7,7,7,4,5",
      "count": 1
    },
    {
      "pattern": "4,4,6,4,4,6,4,4,6,5,4,4,3,4,4,6,4,4,6,4,6,4,5,4,4",
      "count": 1
    },
    {
      "pattern": "4,4,6,4,5,6,3,4,3,4,5,2,3,3,4,5,4,6,3,4,3,4,5",
      "count": 1
    },
    {
      "pattern": "4,3,4,5,4,6,4,4,6,3,4,6,2,4,4,5,4,6,4,4,6,3,4,6",
      "count": 1
    },
    {
      "pattern": "4,6,4,5,4,6,4,4,4,3,3,4,5,4,6,4,4",
      "count": 1
    },
    {
      "pattern": "4,6,4,5,4,6,4,4,4,3,3,4,5,4,3,4,4,4",
      "count": 1
    },
    {
      "pattern": "4,6,7,4,3,4,5,5,4,3,4,7,4,3,4,4,4",
      "count": 1
    },
    {
      "pattern": "7,5,7,3,5,4,4,5,7,5,7,3,4,4,4,5",
      "count": 1
    },
    {
      "pattern": "5,6,6,5,7,5,6,5",
      "count": 1
    },
    {
      "pattern": "4,6,3,4,4,5,3,6,4,4,3,4,4,5,5,4",
      "count": 1
    },
    {
      "pattern": "4,6,3,4,4,5,5,4,4,4,3,4,4,5,5,4",
      "count": 1
    },
    {
      "pattern": "7,3,4,7,3,4,4,6,7,3,4",
      "count": 1
    },
    {
      "pattern": "3,7,3,4,4,7,7,3,4,4",
      "count": 1
    },
    {
      "pattern": "4,4,4,3,4,4,4,7,4,6,4,6,3,4,8,3,4,6,3,4,3,4,6,4",
      "count": 1
    },
    {
      "pattern": "4,4,6,4,4,6,5,5,4,4,7,6,5,4,4,4,6,5,5,4,6,5",
      "count": 1
    },
    {
      "pattern": "6,3,4,6,3,4,7,3,4,6,3,4",
      "count": 1
    },
    {
      "pattern": "5,3,6,5,5,4,4,3,4,5,4,4,2,4,4,4,4,3,3,5,4,6,3,4,4",
      "count": 1
    },
    {
      "pattern": "4,4,6,5,4,6,6,5,4,4,4,4,6,3,4,4,6,6,4,4,4",
      "count": 1
    },
    {
      "pattern": "4,4,6,7,3,4,4,4,6,7,3,4",
      "count": 1
    },
    {
      "pattern": "4,5,7,5,4,3,6,5,4,7,5,4,3,4,3,5,3,6",
      "count": 1
    },
    {
      "pattern": "3,6,3,4,6,3,4,3,4,4,4,7,3,4,5,3,4,4,3,4,6,3,4,3,4,4,4,7,3,4,5,3,4,4",
      "count": 1
    },
    {
      "pattern": "5,3,4,6,6,4,5,3,4,6,4,6",
      "count": 1
    },
    {
      "pattern": "4,5,4,4,6,6,7,3,4,3,4,4,6,3,6,4,5,6,7,3,4,3,6",
      "count": 1
    },
    {
      "pattern": "6,5,4,5,6,6,4,3,6,5,4,5,6,6,4",
      "count": 1
    },
    {
      "pattern": "4,4,4,4,6,3,4,7,3,4,6,2,4,5,4,1,1,6,3,4,7,3,4,5",
      "count": 1
    },
    {
      "pattern": "6,7,7,3,7,7,7,7,3,7",
      "count": 1
    },
    {
      "pattern": "7,3,3,3,5,3,3,7,3,4,5,3,3",
      "count": 1
    },
    {
      "pattern": "4,4,4,4,4,5,4,4,6,3,4,6,4,4,6,4,4,5,4,4,5,3,4,4",
      "count": 1
    },
    {
      "pattern": "5,5,4,4,3,6,4,3,4,3,4,6,6,5,4,4,3,6,4,3,4,3,4,4",
      "count": 1
    },
    {
      "pattern": "7,3,3,7,6,4,4,5,7,3,3,7,6,4,4,5",
      "count": 1
    },
    {
      "pattern": "4,8,4,4,4,6,3,4,4,4,4",
      "count": 1
    },
    {
      "pattern": "4,5,4,3,4,5,4,4,3,4,3,4,6,6,5,4,3,4,5,4,4,3,4,3,4,4",
      "count": 1
    },
    {
      "pattern": "4,4,7,7,7,4,4,7,7,7",
      "count": 1
    },
    {
      "pattern": "4,4,4,3,5,3,3,7,5,3,6,5",
      "count": 1
    },
    {
      "pattern": "4,4,4,5,4,5,7,5,5,4,5",
      "count": 1
    },
    {
      "pattern": "7,5,4,4,4,7,5,4,4,4",
      "count": 1
    },
    {
      "pattern": "5,5,7,5,3,5,5,7,6,3",
      "count": 1
    },
    {
      "pattern": "2,4,5,5,5,7,3,4,7,5",
      "count": 1
    },
    {
      "pattern": "7,3,3,7,3,4,3,5,3,3,7,3,3",
      "count": 1
    },
    {
      "pattern": "4,4,7,6,5,3,7,4,4,3,3,4,3,4,5,3,5,3,5,3,4,6,4,3,7,4,3,3,3,3,4,4,3,4",
      "count": 1
    },
    {
      "pattern": "7,3,4,4,4,6,7,3,4,4,4,7",
      "count": 1
    },
    {
      "pattern": "7,3,4,4,4,6,7,3,4,4,4,6",
      "count": 1
    },
    {
      "pattern": "7,3,4,4,4,6,7,3,4,4,4,3,3",
      "count": 1
    },
    {
      "pattern": "6,3,4,4,4,6,7,3,4,4,4,6",
      "count": 1
    },
    {
      "pattern": "6,3,4,4,4,6,7,3,4,7,3,4",
      "count": 1
    },
    {
      "pattern": "4,4,4,4,3,4,3,4,4,6,4,3,4,3,4,3,4,4",
      "count": 1
    },
    {
      "pattern": "6,4,3,4,3,4,4,4,4,6,4,3,4,3,4,3,8",
      "count": 1
    },
    {
      "pattern": "6,3,6,3,3,3,3,6,3",
      "count": 1
    },
    {
      "pattern": "5,3,4,4,5,3,5,7,3,3,4",
      "count": 1
    },
    {
      "pattern": "7,3,4,3,4,3,4,7,3,4,3,5,3,4",
      "count": 1
    },
    {
      "pattern": "7,3,4,7,3,4,7,3,4,7,6",
      "count": 1
    },
    {
      "pattern": "4,4,6,4,4,6,4,5,4,5,3,4,5,4,6,5,3,4,4,3,4,3,4,6",
      "count": 1
    },
    {
      "pattern": "4,5,4,4,4,5,5,3,3,4,4,4,2,4,3,4,5,4,5,5,7,3,6,4",
      "count": 1
    }
  ],
  "poem_ids": [
    "a5acc00e9e49dffce72f33c0595cb553",
    "82dc71bd0a6f7c45516b2a56bcc2578d",
    "3341b963d1c9dd0501ce7b2521fb2d20",
    "9996a904315aeec78593dd3a5f4aec1c",
    "92d82fdb24d3d3fd31f4936266dd4934",
    "1a996deb3591bac93e16e7584177fc67",
    "ce8aa61dd29e8a8218d8e35d82865dbc",
    "020265791f41e72a9984c226e81a1e73",
    "36f11d19b789f72d0614d622b2961bba",
    "5db1b1dc4c20cb3ab12c7b21bf4a56b8",
    "323a6796bda532f891b8a5a3ecadaed4",
    "858c6bc5ed1067b8febb26b4fbaac76a",
    "260a3d68b3d3ad9568ec17864fd5db08",
    "e276036bbe93d62285bdd87769340dea",
    "ee81b4c35b2daf6e291acff0589acdea",
    "167f97c724aa4ed43fdcc64777d6a40d",
    "cfc7cacaf6677cb559aca85ea692bab5",
    "a887642eb3fbe90ea2a7fe2e17d9ca78",
    "747a242f7f277a31d5ac545b79b5e7ea",
    "cef7a58bb5d2b137165e2020e9cdad84",
    "5e4b59cb2f6379dd2ef59eb1e3c44ea0",
    "e9fe105953aae2995585c5c1505ac784",
    "978c0b322d667c0f4021a3548887d202",
    "d9e8e5494a80314ae8f6ec1d6e920cee",
    "93c52daf70977db7fc39bbef243bc8f0",
    "cd11c8a697290dc7ccbf6abf3d5a29df",
    "81988f4e38bc519782f307853b8f27b7",
    "cf436335974d364e091f3ab15c8e38b3",
    "ddb53c67fd22165a31fa047710f05262",
    "8cbbf69063d6467f4bd1a613a0a61068",
    "99fa99d58ab7d870f92bf34e92e72409",
    "085903deb2f0759ab9b124308b725bff",
    "f941178a3a989db7c7a9695ea50e66db",
    "c7729572404119d92e92d97c62a3f9a7",
    "4129c9a8a8d13c2d62ffee1f787e1551",
    "010a02a44a88f02775fc48df2982b3d9",
    "ae3435d06d167a001dbce3ffbc3150e3",
    "b7192a2a3ba15c4352e95192514dd4b3",
    "ca77849f61aa8f244a94f3f239cd857a",
    "ca8cb472bfee8ee3158f1a4a0afb6290",
    "dd7d3af8e3fae32fd2fb2fde258717e5",
    "f58d1414213c745f35ebf7c63ed12e14",
    "b5c3184da86de7c98df90f6b5abf412d",
    "5cf02380187d8931e1f7783eafe45ae1",
    "25bf4b952c1112fb15cf75fb5a9af33b",
    "0c916ecc7e3e4b7b96b647f4c7ab39a7",
    "4520a554c84dbf2615ed2f70960a2be7",
    "87301c6296aca7d344763fd0e50b97d3",
    "1fe507f364fd60c18c4a0c3f33399742",
    "ae20d75298484bf8d5cf1cc6a3f2bfc6",
    "a1e55ce9f0cd517e538b8bcba2b05c0c",
    "0c00cc9cfe1a8b56f1185548bbf19206",
    "ca758305b4d18b1a579d4b2c983a6010",
    "6a0303849755693ef13e1fb9859ba3b4",
    "ca40cd971eebe45560bd38a5b2cb95b6",
    "255a8d4ac2c6c67409255332e2da3d50",
    "aa94e346d927776014c0266e0d3c2c06",
    "05b72b8dca9f3ed7da10f9786632d23b",
    "f4d32e44c477af267b21c599490deadf",
    "49fa90565358a7697f8a88b250c363ea",
    "c41edd7d91503bd682f3fc3375895974",
    "0248fec0a9411266eedc35e3054ff040",
    "788454e405b65a4a818bc4f0cbb2d1ab",
    "c388a48cadb2e15ba4d3c3023f2c1f47",
    "492898ce00dded63bca27f182f14473b",
    "0f0db48ca1c13e349c18d6c20c3c8983",
    "d92a1b11034d3b0ae398d640d1230004",
    "2d342ef8900c3927c9fbe1b4e99795d3",
    "e0c97c3460db1502da60f1095572f0cc",
    "955434ec83ebc67d9528f985192533d1",
    "95f630abceb48831d73cf57a1d3499d0",
    "406fa5d8baf5f5de73dfc6a5235d0bfb",
    "9b36ed7dc9459b46744d1d9db682bdee",
    "dc5efc30d9009099d8779001e339deae",
    "a6b0280287993a3c8a26f43013cdc38d",
    "cc7ec4999dbb897e8b5980887824823c",
    "a28634cdef5c677c27731adb405e494f",
    "3b36db88ca5f4fc227ecd8dbe92ddc61",
    "da898f2d2120c5c697fb2c8c44702155",
    "cf1ff066e3657e04b3295f29fc0681f5",
    "0873eaeb65d1a1cb972661278c8da077",
    "b7a48e6d5d7c2047fef2beff18887106",
    "270f014adf7a9b79d2948f4cd1d0a7ec",
    "bfe8244bf0ad5b8b3f0bbd935bf244c9",
    "f81ad7c038b3ed2f48645366bfcce296",
    "e1f4347ac66242662b47379cf13c3613",
    "51c8bf9aa66aea531b77a64b6f18c12b",
    "ba9cdc93e108b3db789a2f35cb001638",
    "a717f44dd1bae2c7067f3796404ed167",
    "478e3d40b732d22a227e330fd61f992c",
    "717a001975a7826bcbc4deedeb510d7e",
    "0ff02d818a1eed2fa66e726bb3ed0a45",
    "546c6281d999652187328c3190b9b2cf",
    "b0c00f71efe167e2fe9b8baa6a362f1e",
    "df865f0b50c1c106c278254b52a0918b",
    "64c1dd72205a3752e9db7d0434e2de81",
    "2c470fdf8935c298804a5d07adda6669",
    "02514e51e62e11b2671c5d184ddeff6a",
    "50a89178f8c04e50efc564c4f09a77a8",
    "6eba236357e5a2c16c40946c0d44badb",
    "5ca7cbf7926d47e99a9d643389f07838",
    "df5187fdee43d182b8d54858f721ea6f",
    "27228de6d0143199d8fdc7b9a654e9d2",
    "1b6db238405be9ae5773a386a11080be",
    "6b5c44a81562d995944876ecd669a5ad",
    "f954c1c7095eaeb70cdf90781f85fea0",
    "d4cf861e2d1b85cea3b63fd21224da30",
    "393198efdfcfb652102ad29846468662",
    "062458943b98a9d612032f6a5163fde5",
    "18b974863414d6d87e973c2b67575894",
    "baab64f1eb1793ced5d2fa49ff3813a9",
    "f28d8ccdf15f3d5ef9582f8b21253fe0",
    "aee53ac593a8fdce1000fdcb40c2f92a",
    "7b683a9471f9724c5af5108a519c5d70",
    "c11e4c73f58f303cfb5195a121496520",
    "645c9c8f939ff3742def6e8d131f92f2",
    "38cc77ab0a9316527cf02ee129520be6",
    "bff3f28e161018dea97505d0526dc38f",
    "e09b162a973e73a344e99ee57ee8c5cd",
    "bea5a10ebf225c80d495eb2a13a69c75",
    "4467e5a2b43374b352971e9e2deee04f",
    "0c23722fd240426b25a9df220ae691f6",
    "2a40c05a25b71579d3d85ee405a75682",
    "922f1c912fc3eb0c2bbb4a98b1352951",
    "b2d1b0345ad1b85fb13782b6df9aabc7",
    "14dd8ad5c46c1db3a4e6ed7a2bb0c494",
    "435688a55b3899a3874ee6fee47202cc",
    "8bc0fb412c7f3e7bfb2e3813057bc9d4",
    "16a559334e4bb3c4b8504f1e2272990b",
    "9721b23057c077831a47bc59133044f8",
    "7d4b3666c25219fe33bad9fbca21c829",
    "4368e110123fdd722f433ea4bae0380c",
    "00613b11f768ff1e6602bcf2f621478c",
    "27c9af16feece0e97e157f043308db25",
    "fe5eda59389422cfda98c11bd169c2d8",
    "f3910eb15145cd6330c7af8e0a2022fd",
    "f4bfb6bec3aeb83d36ed30a2ff5d632d",
    "acb320b3cc45e2fe669491ea6edd8450",
    "6e72edf9828defec9bd34e39e2855f9f",
    "0d5a5879714a04f8a4477757c57e0472",
    "324631d15ba9bd03bb42f9a45c4defa4",
    "0231152fde321bf6523b6c7e63a793d8",
    "1dd66415a02264d125cb3fc33755ca9c",
    "3f97aba6f62dc42a731fcd50af78bb8f",
    "3e5826466120e16ca230d0e2a8f38a49",
    "2c8b94bc434f9d37096aab162419c70f",
    "2b1e14cb20c3c65eba587e9f32bce409",
    "7a7cce93756a881da50f9e2d7380fa5a",
    "069ef224803ebc974d14333c42f3ef1b",
    "2cfcc8eeac526ff7554a86d9eb69510a",
    "04320432018b3cc4f0750d9742d836d2",
    "9003eb216c3d7d4c8fae4d4cba1a2662",
    "386c23c1e3a965bcee7df058eaffad54",
    "3023e825fd9343c19bfddf24d1eecee3",
    "fb40bfa151b320bbd1fe0e5f0415ecd3",
    "f22a6cb12b0e8c5c3e41875df9452660",
    "177e63811d60e633e9958d7448c8a9f8",
    "75fb1445ecad8a6d26814ec67e6bc2b6",
    "caec5155dea213a17d858c036ed104d0",
    "3125f4525d99ceba34c493608e30956f",
    "6c278308f6716421c388cb2620363afb",
    "f644de2d54396709032f4e074e650b58",
    "1fdf29385b98a855bd0ea46d5711b7e6",
    "78fb0e2f4abbde220dfd52502c791489",
    "3b4150015fdfa51a30b90af021491a59",
    "2e1ddfea4f4bfc521d8a5b712e7900a2",
    "c20027da355c4c5b092e4d111c9b656a",
    "64c0a724045e10e4d071c2ed54e6b61f",
    "fa80f8caef3ba15073a39cf8fa6ae5d2",
    "2eca0ee051b2367556f29f930f50bbc0",
    "c105316623226bc89d7b555446d13298",
    "d159ef2d08393f9454b4f3371e61ef4b",
    "e4c09cadfaad4c93d273f54430db1a49",
    "931873ea60a11e33c83464abcc697421",
    "1bfe784a3c6be886e6f246b05e4af9a5",
    "685a380fa28408eb4672fd841f2046a8",
    "e8e3bcb045f1590c8943592716c95469"
  ],
  "word_frequency": {
    "□": 60,
    "谁": 54,
    "人": 47,
    "是": 35,
    "又": 34,
    "为": 33,
    "在": 31,
    "看": 31,
    "更": 30,
    "不": 28,
    "与": 28,
    "有": 27,
    "我": 27,
    "处": 27,
    "月": 27,
    "好": 23,
    "听": 23,
    "对": 22,
    "来": 22,
    "见": 21,
    "欲": 20,
    "去": 19,
    "也": 19,
    "却": 18,
    "应": 18,
    "和": 18,
    "还": 18,
    "似": 17,
    "如": 17,
    "未": 17,
    "向": 17,
    "春": 17,
    "风流": 16,
    "问": 16,
    "中": 16,
    "香": 16,
    "里": 15,
    "知": 15,
    "一": 15,
    "尽": 15,
    "酒": 15,
    "清": 14,
    "时": 14,
    "记": 14,
    "可": 14,
    "已": 14,
    "岁": 14,
    "馀": 14,
    "只": 14,
    "笑": 14,
    "同": 13,
    "梦": 13,
    "愁": 13,
    "新": 13,
    "得": 13,
    "凭": 12,
    "雨": 12,
    "满": 12,
    "初": 12,
    "恨": 12,
    "低": 12,
    "君": 12,
    "前": 12,
    "到": 12,
    "且": 12,
    "醉": 12,
    "长": 12,
    "无": 12,
    "红": 11,
    "曾": 11,
    "云": 11,
    "暖": 11,
    "惊": 10,
    "成": 10,
    "花": 10,
    "风": 10,
    "上": 10,
    "正": 10,
    "将": 10,
    "轻": 10,
    "共": 10,
    "日": 10,
    "愿": 10,
    "春风": 10,
    "喜": 9,
    "他": 9,
    "声": 9,
    "年": 9,
    "傍": 9,
    "占": 9,
    "伊": 9,
    "须": 9,
    "风味": 8,
    "待": 8,
    "入": 8,
    "水": 8,
    "气": 8,
    "地": 8,
    "老": 8,
    "吹": 8
  },
  "similar_authors": [
    {
      "author": "无名氏",
      "similarity": 0.6714
    },
    {
      "author": "辛弃疾",
      "similarity": 0.6422
    },
    {
      "author": "赵长卿",
      "similarity": 0.6347
    },
    {
      "author": "刘辰翁",
      "similarity": 0.6114
    },
    {
      "author": "周紫芝",
      "similarity": 0.5954
    },
    {
      "author": "周邦彦",
      "similarity": 0.584
    },
    {
      "author": "杨万里",
      "similarity": 0.5835
    },
    {
      "author": "吴潜",
      "similarity": 0.5824
    },
    {
      "author": "李之仪",
      "similarity": 0.5824
    },
    {
      "author": "韩淲",
      "similarity": 0.582
    }
  ]
}